smartem/__init__.py
smartem/stage_model.py
smartem/cli/__init__.py
smartem/cli/change_epu_directory.py
smartem/cli/export.py
smartem/cli/initialise.py
smartem/cli/launch.py
smartem/cli/missing.py
smartem/cli/quick_epu_viewer.py
smartem/cli/start.py
smartem/cli/stop.py
smartem/data_model/__init__.py
smartem/data_model/construct.py
smartem/data_model/extract.py
smartem/data_model/structure.py
smartem/data_model/torch.py
smartem/gui/__init__.py
smartem/gui/atlas/__init__.py
smartem/gui/atlas/main.py
smartem/gui/qt/__init__.py
smartem/gui/qt/component_tab.py
smartem/gui/qt/display.py
smartem/gui/qt/image_utils.py
smartem/gui/qt/loader.py
smartem/gui/qt/loader_csv.py
smartem/gui/qt/plotting_utils.py
smartem/gui/qt/qt_style.css
smartem/parsing/__init__.py
smartem/parsing/epu.py
smartem/parsing/epu_vis.py
smartem/parsing/export.py
smartem/parsing/relion_default.py
smartem/parsing/star.py
smartem-0.2.0.dist-info/LICENSE
smartem-0.2.0.dist-info/METADATA
smartem-0.2.0.dist-info/WHEEL
smartem-0.2.0.dist-info/entry_points.txt
smartem-0.2.0.dist-info/top_level.txt
smartem-0.2.0.dist-info/RECORD
