Metadata-Version: 2.1
Name: smartem
Version: 0.2.0
Summary: Tool to trace cryoEM SPA processing results through the magnification hierarchy provided by EPU
Requires-Python: >=3.8
License-File: LICENSE
Requires-Dist: gemmi
Requires-Dist: matplotlib
Requires-Dist: xmltodict
Requires-Dist: mrcfile
Requires-Dist: pyyaml
Requires-Dist: pandas
Requires-Dist: plotly
Requires-Dist: tifffile
Provides-Extra: db
Requires-Dist: psycopg2; extra == "db"
Requires-Dist: sqlalchemy<2.0; extra == "db"
Provides-Extra: old_vis
Requires-Dist: PyQt5; extra == "old-vis"
Provides-Extra: vis
Requires-Dist: solara; extra == "vis"
